{"blocks":[{"depth":380,"id":"seat","width":450,"x":100,"y":140},{"depth":120,"id":"backrest","width":410,"x":120,"y":40},{"depth":100,"id":"base","width":250,"x":200,"y":500}],"checksum":"fd715bc84aab56ac417d0a185d2a2087fba0178268d86c0b8dc36db0661e3202","createdBy":"seed-block-descriptors-brand-heroes","fixed":{"sizingType":"fixed"},"generatedAt":1752000050,"geometry":{"depthMm":650,"heightMm":1100,"widthMm":650},"id":"a81e3a1b-16f4-4000-8000-000000000019","liveAnnouncementCategories":["status"],"mounting":["floor"],"rovingFocus":[],"schemaVersion":"2026-07-04.v2","sku":"OANDO-BREEZE-CHR-TSK","slug":"oando-breeze-task-chair","sourceProvenance":"native","themeTokens":{"--fill-primary":"var(--color-surface-raised)","--stroke-accent":"var(--color-border)","currentColor":"currentColor"},"variant":"fixed","viewBox":{"height":650,"width":650,"x":0,"y":0}}
