{
    "name":  "phase1a-open3d-vitest-pass",
    "module":  "open3d",
    "phase":  "phase-1",
    "command":  "pnpm --filter oando-site exec vitest run tests/unit/features/planner/open3d/workspaceShell.test.tsx tests/unit/features/planner/open3d/open3dFeasibilityCanvas.test.tsx --config vitest.site.config.ts --reporter=verbose 2\u003e\u00261 | Out-String -Width 4096",
    "cwd":  "D:\\oandO04072026",
    "operator":  "Oz agent (Warp CLI session)",
    "startUtc":  "2026-07-05T23:30:49.2870431+05:30",
    "endUtc":  "2026-07-05T23:30:58.0710441+05:30",
    "durationSec":  8.784,
    "exitCode":  0,
    "rawLog":  "D:\\oandO04072026\\results\\open3d\\phase-1\\phase1a-open3d-vitest-pass\\phase1a-open3d-vitest-pass-raw.log"
}
