{"numTotalTestSuites":2,"numPassedTestSuites":2,"numFailedTestSuites":0,"numPendingTestSuites":0,"numTotalTests":7,"numPassedTests":7,"numFailedTests":0,"numPendingTests":0,"numTodoTests":0,"snapshot":{"added":0,"failure":false,"filesAdded":0,"filesRemoved":0,"filesRemovedList":[],"filesUnmatched":0,"filesUpdated":0,"matched":0,"total":0,"unchecked":0,"uncheckedKeysByFile":[],"unmatched":0,"updated":0,"didUpdate":false},"startTime":1783604315876,"success":true,"testResults":[{"assertionResults":[{"ancestorTitles":["cabinet-v0 Block2D plan symbol (W2)"],"fullName":"cabinet-v0 Block2D plan symbol (W2) uses placed modular dimensions for footprint","status":"passed","title":"uses placed modular dimensions for footprint","duration":1.4601000000000113,"failureMessages":[],"meta":{},"tags":[]},{"ancestorTitles":["cabinet-v0 Block2D plan symbol (W2)"],"fullName":"cabinet-v0 Block2D plan symbol (W2) is not an empty-box symbol: ≥4 prims with carcass + front + door cue","status":"passed","title":"is not an empty-box symbol: ≥4 prims with carcass + front + door cue","duration":0.48659999999995307,"failureMessages":[],"meta":{},"tags":[]},{"ancestorTitles":["cabinet-v0 Block2D plan symbol (W2)"],"fullName":"cabinet-v0 Block2D plan symbol (W2) keeps all prim geometry inside footprint (no runaway coords)","status":"passed","title":"keeps all prim geometry inside footprint (no runaway coords)","duration":0.5917999999999211,"failureMessages":[],"meta":{},"tags":[]},{"ancestorTitles":["cabinet-v0 Block2D plan symbol (W2)"],"fullName":"cabinet-v0 Block2D plan symbol (W2) pair doors get a center stile; slab does not","status":"passed","title":"pair doors get a center stile; slab does not","duration":0.27919999999994616,"failureMessages":[],"meta":{},"tags":[]},{"ancestorTitles":["cabinet-v0 Block2D plan symbol (W2)"],"fullName":"cabinet-v0 Block2D plan symbol (W2) reports top-left prim authorship (centeredPath helper is false)","status":"passed","title":"reports top-left prim authorship (centeredPath helper is false)","duration":0.1776999999999589,"failureMessages":[],"meta":{},"tags":[]},{"ancestorTitles":["cabinet-v0 Block2D plan symbol (W2)"],"fullName":"cabinet-v0 Block2D plan symbol (W2) renders to canvas without throwing and issues fill+stroke","status":"passed","title":"renders to canvas without throwing and issues fill+stroke","duration":1.3781000000001313,"failureMessages":[],"meta":{},"tags":[]},{"ancestorTitles":["cabinet-v0 Block2D plan symbol (W2)"],"fullName":"cabinet-v0 Block2D plan symbol (W2) never depends on external SVG/GLB URLs for plan symbol","status":"passed","title":"never depends on external SVG/GLB URLs for plan symbol","duration":0.3790999999998803,"failureMessages":[],"meta":{},"tags":[]}],"startTime":1783604317457,"endTime":1783604317462.3792,"status":"passed","message":"","name":"D:/OandO07072026/site/tests/unit/features/planner/open3d/catalog/furnitureBlock2D.cabinet-v0.test.ts"}]}